odoo/addons/l10n_de_country_states/README.rst
odoo/addons/l10n_de_country_states/__init__.py
odoo/addons/l10n_de_country_states/__manifest__.py
odoo/addons/l10n_de_country_states/data/res_country_states.xml
odoo/addons/l10n_de_country_states/i18n/de.po
odoo/addons/l10n_de_country_states/i18n/l10n_de_country_states.pot
odoo/addons/l10n_de_country_states/static/description/icon.png
odoo11_addon_l10n_de_country_states-11.0.1.0.0.99.dev4.dist-info/METADATA
odoo11_addon_l10n_de_country_states-11.0.1.0.0.99.dev4.dist-info/RECORD
odoo11_addon_l10n_de_country_states-11.0.1.0.0.99.dev4.dist-info/WHEEL
odoo11_addon_l10n_de_country_states-11.0.1.0.0.99.dev4.dist-info/top_level.txt
